aiohttp_validate/__init__.py
aiohttp_validate-1.0.0.dist-info/DESCRIPTION.rst
aiohttp_validate-1.0.0.dist-info/METADATA
aiohttp_validate-1.0.0.dist-info/RECORD
aiohttp_validate-1.0.0.dist-info/WHEEL
aiohttp_validate-1.0.0.dist-info/entry_points.txt
aiohttp_validate-1.0.0.dist-info/metadata.json
aiohttp_validate-1.0.0.dist-info/top_level.txt
