Metadata-Version: 2.0
Name: aiohttp-validate
Version: 1.0.0
Summary: Simple library that helps you validate your API endpoints requests/responses with json schema
Home-page: https://github.com/dchaplinsky/aiohttp_validate
Author: Dmitry Chaplinsky
Author-email: chaplinsky.dmitry@gmail.com
License: MIT license
Keywords: aiohttp_validate
Platform: UNKNOWN
Classifier: Development Status :: 5 - Production/Stable
Classifier: Intended Audience :: Developers
Classifier: License :: OSI Approved :: MIT License
Classifier: Natural Language :: English
Classifier: Programming Language :: Python :: 3
Classifier: Programming Language :: Python :: 3.5
Requires-Dist: aiohttp (==1.0.5)
Requires-Dist: jsonschema (==2.5.1)
